Workbook

Sheet Cover
A1: SALES PERFORMANCE PORTFOLIO
B4: ATK Sejahtera • Transaction Analysis, January to December 2026
B6: Prepared by Rifal Azhar Permana
B7: Data Analyst Portfolio Project
B11: TOTAL REVENUE (Rp) | G11: GROSS MARGIN | L11: REVENUE GROWTH (JAN TO DEC)
B12: =Summary!B6 -> 99664000 | G12: =Summary!B8 -> 0.38813212 | L12: ="+"&TEXT('Monthly Analysis'!H16-1,"0%") -> +40%
B16: WHAT THIS FILE DEMONSTRATES
B17: • I cleaned and structured 288 rows of raw transaction data from 3 branches, then built a connected analysis system (not static numbers) using SUMIFS, INDEX/MATCH, and IFERROR.
B19: • Interactive dashboard with a branch filter: once the branch changes, every KPI card and chart updates automatically, no manual formula edits needed.
B21: • Real business insight in the Summary sheet, not just a recap of numbers, but conclusions that can support decisions (for example, which product is profitable but has a 'thinning' margin).
B24: Contact: rifalazharpermana@gmail.com • https://www.linkedin.com/in/rifalazharpermana/ • This file was built entirely in Excel, without a third-party template.

Sheet Dashboard
A1: SALES PERFORMANCE DASHBOARD
A2: ATK Sejahtera • January to December 2026 • Prepared by Rifal Azhar Permana
E4: Branch | F4: All Branches | H4: Select a branch to update the KPI cards and charts.
A6: TOTAL REVENUE (Rp) | D6: GROSS PROFIT (Rp) | G6: GROSS MARGIN | J6: UNITS SOLD | M6: AVG. REVENUE / TRANSACTION (Rp)
A7: =IF($F$4="All Branches",SUM('Raw Data'!$K$5:$K$292),SUMIFS('Raw Data'!$K$5:$K$292,'Raw Data'!$A$5:$A$292,$F$4)) -> 99664000 | D7: =IF($F$4="All Branches",SUM('Raw Data'!$M$5:$M$292),SUMIFS('Raw Data'!$M$5:$M$292,'Raw Data'!$A$5:$A$292,$F$4)) -> 38682800 | G7: =IFERROR(D7/A7,0) -> 0.38813212 | J7: =IF($F$4="All Branches",SUM('Raw Data'!$E$5:$E$292),SUMIFS('Raw Data'!$E$5:$E$292,'Raw Data'!$A$5:$A$292,$F$4)) -> 12235 | M7: =IFERROR(A7/COUNTA('Raw Data'!$A$5:$A$292),0) -> 346055.56
A10: MONTHLY REVENUE | I10: REVENUE BY PRODUCT
A27: REVENUE BY BRANCH | I27: REVENUE MIX BY CATEGORY
A45: KEY FINDINGS
A46: Use the branch selector above to compare performance. The detailed product, branch, monthly and customer tables are in the analysis sheets.

Sheet Overview
A1: SALES ANALYTICS PORTFOLIO
A2: Excel Portfolio • ATK Sejahtera • 2026 • by Rifal Azhar Permana
A4: ABOUT THE FILE
A5: I built this file from raw transaction data for ATK Sejahtera's 3 branches across one full year (January to December 2026). The goal wasn't just to clean up numbers, but to build an analysis flow that can be reused: from raw data, to helper tables, to a dashboard that can be filtered by branch. Every number across every sheet is connected through formulas, so if the raw data changes, the whole report updates automatically.
A9: WORKBOOK STRUCTURE | F9: WHAT I USED
A10: Dashboard | B10: Main view and branch filter | F10: Data cleaning | G10: Calculated month number, revenue, COGS and gross profit
A11: Raw Data | B11: Transaction-level source data | F11: Analysis | G11: SUMIFS, INDEX/MATCH, IFERROR, RANK
A12: Sales Analysis | B12: Product performance | F12: Dashboard | G12: Charts, KPI cards and a branch selector
A13: Branch Analysis | B13: Branch and category performance
A14: Monthly Analysis | B14: Monthly trend and growth
A15: Customer Analysis | B15: Customer and sales rep contribution
A16: Summary | B16: Key metrics and findings
A17: Calculations | B17: Helper tables for dashboard charts
A20: Note: The source data does not contain a discount field, so this portfolio does not invent a “net revenue” metric.
A22: MY APPROACH
A23: 1. Data cleaning first. I checked the raw data to make sure there were no duplicate or empty rows, then added a helper column (Month No.) so it could be sorted chronologically instead of alphabetically.
A25: 2. I intentionally avoided PivotTables so the whole logic stays transparent through formulas (SUMIFS/INDEX-MATCH). It's easier for someone else to audit, and I can explain every number if asked.
A27: 3. Cross-check: I compared total revenue on the Dashboard, the Summary, and a manual SUM from Raw Data, and they all matched exactly (Rp99,664,000), so no formula points in the wrong direction.
A29: 4. The insights on the Summary sheet are based on patterns that actually show up in the data, not a generic template, for example the finding about Notebook's margin below.

Sheet Raw Data
A1: SALES DATA
A2: Source data + calculated fields used in the workbook
A4: Branch | B4: Product | C4: Category | D4: Month | E4: Units Sold | F4: Unit Price (Rp) | G4: Unit Cost (Rp) | H4: Sales Rep | I4: Customer | J4: Month No. | K4: Revenue (Rp) | L4: COGS (Rp) | M4: Gross Profit (Rp) | N4: Gross Margin
A5: Bandung | B5: Notebook | C5: Paper Products | D5: January | E5: 26 | F5: 25000 | G5: 17000 | H5: Andi Prasetyo | I5: Toko Berkah Jaya | J5: =MATCH(D5,Calculations!$A$5:$A$16,0) -> 1 | K5: =E5*F5 -> 650000 | L5: =E5*G5 -> 442000 | M5: =K5-L5 -> 208000 | N5: =IFERROR(M5/K5,0) -> 0.32
A6: Bandung | B6: Notebook | C6: Paper Products | D6: February | E6: 28 | F6: 25000 | G6: 17000 | H6: Sri Wulandari | I6: CV Sumber Makmur | J6: =MATCH(D6,Calculations!$A$5:$A$16,0) -> 2 | K6: =E6*F6 -> 700000 | L6: =E6*G6 -> 476000 | M6: =K6-L6 -> 224000 | N6: =IFERROR(M6/K6,0) -> 0.32
A7: Bandung | B7: Notebook | C7: Paper Products | D7: March | E7: 31 | F7: 25000 | G7: 17000 | H7: Andi Prasetyo | I7: Sekolah Tunas Bangsa | J7: =MATCH(D7,Calculations!$A$5:$A$16,0) -> 3 | K7: =E7*F7 -> 775000 | L7: =E7*G7 -> 527000 | M7: =K7-L7 -> 248000 | N7: =IFERROR(M7/K7,0) -> 0.32
A8: Bandung | B8: Notebook | C8: Paper Products | D8: April | E8: 30 | F8: 25000 | G8: 17000 | H8: Sri Wulandari | I8: Toko Berkah Jaya | J8: =MATCH(D8,Calculations!$A$5:$A$16,0) -> 4 | K8: =E8*F8 -> 750000 | L8: =E8*G8 -> 510000 | M8: =K8-L8 -> 240000 | N8: =IFERROR(M8/K8,0) -> 0.32
A9: Bandung | B9: Notebook | C9: Paper Products | D9: May | E9: 32 | F9: 25000 | G9: 17000 | H9: Andi Prasetyo | I9: CV Sumber Makmur | J9: =MATCH(D9,Calculations!$A$5:$A$16,0) -> 5 | K9: =E9*F9 -> 800000 | L9: =E9*G9 -> 544000 | M9: =K9-L9 -> 256000 | N9: =IFERROR(M9/K9,0) -> 0.32
A10: Bandung | B10: Notebook | C10: Paper Products | D10: June | E10: 31 | F10: 25000 | G10: 17000 | H10: Sri Wulandari | I10: Sekolah Tunas Bangsa | J10: =MATCH(D10,Calculations!$A$5:$A$16,0) -> 6 | K10: =E10*F10 -> 775000 | L10: =E10*G10 -> 527000 | M10: =K10-L10 -> 248000 | N10: =IFERROR(M10/K10,0) -> 0.32
A11: Bandung | B11: Notebook | C11: Paper Products | D11: July | E11: 33 | F11: 25000 | G11: 17000 | H11: Andi Prasetyo | I11: Toko Berkah Jaya | J11: =MATCH(D11,Calculations!$A$5:$A$16,0) -> 7 | K11: =E11*F11 -> 825000 | L11: =E11*G11 -> 561000 | M11: =K11-L11 -> 264000 | N11: =IFERROR(M11/K11,0) -> 0.32
A12: Bandung | B12: Notebook | C12: Paper Products | D12: August | E12: 36 | F12: 25000 | G12: 17000 | H12: Sri Wulandari | I12: CV Sumber Makmur | J12: =MATCH(D12,Calculations!$A$5:$A$16,0) -> 8 | K12: =E12*F12 -> 900000 | L12: =E12*G12 -> 612000 | M12: =K12-L12 -> 288000 | N12: =IFERROR(M12/K12,0) -> 0.32
A13: Bandung | B13: Notebook | C13: Paper Products | D13: September | E13: 34 | F13: 25000 | G13: 17000 | H13: Andi Prasetyo | I13: Sekolah Tunas Bangsa | J13: =MATCH(D13,Calculations!$A$5:$A$16,0) -> 9 | K13: =E13*F13 -> 850000 | L13: =E13*G13 -> 578000 | M13: =K13-L13 -> 272000 | N13: =IFERROR(M13/K13,0) -> 0.32
A14: Bandung | B14: Notebook | C14: Paper Products | D14: October | E14: 37 | F14: 25000 | G14: 17000 | H14: Sri Wulandari | I14: Toko Berkah Jaya | J14: =MATCH(D14,Calculations!$A$5:$A$16,0) -> 10 | K14: =E14*F14 -> 925000 | L14: =E14*G14 -> 629000 | M14: =K14-L14 -> 296000 | N14: =IFERROR(M14/K14,0) -> 0.32
A15: Bandung | B15: Notebook | C15: Paper Products | D15: November | E15: 36 | F15: 25000 | G15: 17000 | H15: Andi Prasetyo | I15: CV Sumber Makmur | J15: =MATCH(D15,Calculations!$A$5:$A$16,0) -> 11 | K15: =E15*F15 -> 900000 | L15: =E15*G15 -> 612000 | M15: =K15-L15 -> 288000 | N15: =IFERROR(M15/K15,0) -> 0.32
A16: Bandung | B16: Notebook | C16: Paper Products | D16: December | E16: 38 | F16: 25000 | G16: 17000 | H16: Sri Wulandari | I16: Sekolah Tunas Bangsa | J16: =MATCH(D16,Calculations!$A$5:$A$16,0) -> 12 | K16: =E16*F16 -> 950000 | L16: =E16*G16 -> 646000 | M16: =K16-L16 -> 304000 | N16: =IFERROR(M16/K16,0) -> 0.32
... A292: Surabaya | B292: Eraser | C292: Accessories | D292: December | E292: 40 | F292: 4000 | G292: 2200 | H292: Dedi Hermawan | I292: Toko Ceria | J292: =MATCH(D292,Calculations!$A$5:$A$16,0) -> 12 | K292: =E292*F292 -> 160000 | L292: =E292*G292 -> 88000 | M292: =K292-L292 -> 72000 | N292: =IFERROR(M292/K292,0) -> 0.45

Sheet Sales Analysis
A1: PRODUCT ANALYSIS
A2: Product sales, profit and margin
A4: Product | B4: Category | C4: Unit Price (Rp) | D4: Unit Cost (Rp) | E4: Units Sold | F4: Revenue (Rp) | G4: COGS (Rp) | H4: Gross Profit (Rp) | I4: Margin % | J4: Revenue Share | K4: Growth Jan-Dec | L4: Rank
A5: Ballpoint Pen | B5: =INDEX('Raw Data'!$C$5:$C$292,MATCH(A5,'Raw Data'!$B$5:$B$292,0)) -> Writing Tools | C5: =INDEX('Raw Data'!$F$5:$F$292,MATCH(A5,'Raw Data'!$B$5:$B$292,0)) -> 5000 | D5: =INDEX('Raw Data'!$G$5:$G$292,MATCH(A5,'Raw Data'!$B$5:$B$292,0)) -> 3000 | E5: =SUMIFS('Raw Data'!$E$5:$E$292,'Raw Data'!$B$5:$B$292,A5) -> 2833 | F5: =SUMIFS('Raw Data'!$K$5:$K$292,'Raw Data'!$B$5:$B$292,A5) -> 14165000 | G5: =SUMIFS('Raw Data'!$L$5:$L$292,'Raw Data'!$B$5:$B$292,A5) -> 8499000 | H5: =F5-G5 -> 5666000 | I5: =IFERROR(H5/F5,0) -> 0.4 | J5: =IFERROR(F5/SUM($F$5:$F$12),0) -> 0.14212755 | K5: =IFERROR((SUMIFS('Raw Data'!$K$5:$K$292,'Raw Data'!$B$5:$B$292,A5,'Raw Data'!$D$5:$D$292,"December")/SUMIFS('Raw Data'!$K$5:$K$292,'Raw Data'!$B$5:$B$292,A5,'Raw Data'!$D$5:$D$292,"January"))-1,0) -> 0.345 | L5: =RANK(F5,$F$5:$F$12,0) -> 2
A6: Correction Tape | B6: =INDEX('Raw Data'!$C$5:$C$292,MATCH(A6,'Raw Data'!$B$5:$B$292,0)) -> Accessories | C6: =INDEX('Raw Data'!$F$5:$F$292,MATCH(A6,'Raw Data'!$B$5:$B$292,0)) -> 9000 | D6: =INDEX('Raw Data'!$G$5:$G$292,MATCH(A6,'Raw Data'!$B$5:$B$292,0)) -> 5000 | E6: =SUMIFS('Raw Data'!$E$5:$E$292,'Raw Data'!$B$5:$B$292,A6) -> 1134 | F6: =SUMIFS('Raw Data'!$K$5:$K$292,'Raw Data'!$B$5:$B$292,A6) -> 10206000 | G6: =SUMIFS('Raw Data'!$L$5:$L$292,'Raw Data'!$B$5:$B$292,A6) -> 5670000 | H6: =F6-G6 -> 4536000 | I6: =IFERROR(H6/F6,0) -> 0.44444444 | J6: =IFERROR(F6/SUM($F$5:$F$12),0) -> 0.10240408 | K6: =IFERROR((SUMIFS('Raw Data'!$K$5:$K$292,'Raw Data'!$B$5:$B$292,A6,'Raw Data'!$D$5:$D$292,"December")/SUMIFS('Raw Data'!$K$5:$K$292,'Raw Data'!$B$5:$B$292,A6,'Raw Data'!$D$5:$D$292,"January"))-1,0) -> 0.3625 | L6: =RANK(F6,$F$5:$F$12,0) -> 5
A7: Eraser | B7: =INDEX('Raw Data'!$C$5:$C$292,MATCH(A7,'Raw Data'!$B$5:$B$292,0)) -> Accessories | C7: =INDEX('Raw Data'!$F$5:$F$292,MATCH(A7,'Raw Data'!$B$5:$B$292,0)) -> 4000 | D7: =INDEX('Raw Data'!$G$5:$G$292,MATCH(A7,'Raw Data'!$B$5:$B$292,0)) -> 2200 | E7: =SUMIFS('Raw Data'!$E$5:$E$292,'Raw Data'!$B$5:$B$292,A7) -> 1659 | F7: =SUMIFS('Raw Data'!$K$5:$K$292,'Raw Data'!$B$5:$B$292,A7) -> 6636000 | G7: =SUMIFS('Raw Data'!$L$5:$L$292,'Raw Data'!$B$5:$B$292,A7) -> 3649800 | H7: =F7-G7 -> 2986200 | I7: =IFERROR(H7/F7,0) -> 0.45 | J7: =IFERROR(F7/SUM($F$5:$F$12),0) -> 0.066583721 | K7: =IFERROR((SUMIFS('Raw Data'!$K$5:$K$292,'Raw Data'!$B$5:$B$292,A7,'Raw Data'!$D$5:$D$292,"December")/SUMIFS('Raw Data'!$K$5:$K$292,'Raw Data'!$B$5:$B$292,A7,'Raw Data'!$D$5:$D$292,"January"))-1,0) -> 0.40869565 | L7: =RANK(F7,$F$5:$F$12,0) -> 8
A8: Highlighter | B8: =INDEX('Raw Data'!$C$5:$C$292,MATCH(A8,'Raw Data'!$B$5:$B$292,0)) -> Writing Tools | C8: =INDEX('Raw Data'!$F$5:$F$292,MATCH(A8,'Raw Data'!$B$5:$B$292,0)) -> 12000 | D8: =INDEX('Raw Data'!$G$5:$G$292,MATCH(A8,'Raw Data'!$B$5:$B$292,0)) -> 7000 | E8: =SUMIFS('Raw Data'!$E$5:$E$292,'Raw Data'!$B$5:$B$292,A8) -> 942 | F8: =SUMIFS('Raw Data'!$K$5:$K$292,'Raw Data'!$B$5:$B$292,A8) -> 11304000 | G8: =SUMIFS('Raw Data'!$L$5:$L$292,'Raw Data'!$B$5:$B$292,A8) -> 6594000 | H8: =F8-G8 -> 4710000 | I8: =IFERROR(H8/F8,0) -> 0.41666667 | J8: =IFERROR(F8/SUM($F$5:$F$12),0) -> 0.11342109 | K8: =IFERROR((SUMIFS('Raw Data'!$K$5:$K$292,'Raw Data'!$B$5:$B$292,A8,'Raw Data'!$D$5:$D$292,"December")/SUMIFS('Raw Data'!$K$5:$K$292,'Raw Data'!$B$5:$B$292,A8,'Raw Data'!$D$5:$D$292,"January"))-1,0) -> 0.37878788 | L8: =RANK(F8,$F$5:$F$12,0) -> 4
A9: Notebook | B9: =INDEX('Raw Data'!$C$5:$C$292,MATCH(A9,'Raw Data'!$B$5:$B$292,0)) -> Paper Products | C9: =INDEX('Raw Data'!$F$5:$F$292,MATCH(A9,'Raw Data'!$B$5:$B$292,0)) -> 25000 | D9: =INDEX('Raw Data'!$G$5:$G$292,MATCH(A9,'Raw Data'!$B$5:$B$292,0)) -> 17000 | E9: =SUMIFS('Raw Data'!$E$5:$E$292,'Raw Data'!$B$5:$B$292,A9) -> 1182 | F9: =SUMIFS('Raw Data'!$K$5:$K$292,'Raw Data'!$B$5:$B$292,A9) -> 29550000 | G9: =SUMIFS('Raw Data'!$L$5:$L$292,'Raw Data'!$B$5:$B$292,A9) -> 20094000 | H9: =F9-G9 -> 9456000 | I9: =IFERROR(H9/F9,0) -> 0.32 | J9: =IFERROR(F9/SUM($F$5:$F$12),0) -> 0.29649623 | K9: =IFERROR((SUMIFS('Raw Data'!$K$5:$K$292,'Raw Data'!$B$5:$B$292,A9,'Raw Data'!$D$5:$D$292,"December")/SUMIFS('Raw Data'!$K$5:$K$292,'Raw Data'!$B$5:$B$292,A9,'Raw Data'!$D$5:$D$292,"January"))-1,0) -> 0.4625 | L9: =RANK(F9,$F$5:$F$12,0) -> 1
A10: Pencil | B10: =INDEX('Raw Data'!$C$5:$C$292,MATCH(A10,'Raw Data'!$B$5:$B$292,0)) -> Writing Tools | C10: =INDEX('Raw Data'!$F$5:$F$292,MATCH(A10,'Raw Data'!$B$5:$B$292,0)) -> 3000 | D10: =INDEX('Raw Data'!$G$5:$G$292,MATCH(A10,'Raw Data'!$B$5:$B$292,0)) -> 1800 | E10: =SUMIFS('Raw Data'!$E$5:$E$292,'Raw Data'!$B$5:$B$292,A10) -> 2598 | F10: =SUMIFS('Raw Data'!$K$5:$K$292,'Raw Data'!$B$5:$B$292,A10) -> 7794000 | G10: =SUMIFS('Raw Data'!$L$5:$L$292,'Raw Data'!$B$5:$B$292,A10) -> 4676400 | H10: =F10-G10 -> 3117600 | I10: =IFERROR(H10/F10,0) -> 0.4 | J10: =IFERROR(F10/SUM($F$5:$F$12),0) -> 0.078202761 | K10: =IFERROR((SUMIFS('Raw Data'!$K$5:$K$292,'Raw Data'!$B$5:$B$292,A10,'Raw Data'!$D$5:$D$292,"December")/SUMIFS('Raw Data'!$K$5:$K$292,'Raw Data'!$B$5:$B$292,A10,'Raw Data'!$D$5:$D$292,"January"))-1,0) -> 0.33695652 | L10: =RANK(F10,$F$5:$F$12,0) -> 6
A11: Ruler | B11: =INDEX('Raw Data'!$C$5:$C$292,MATCH(A11,'Raw Data'!$B$5:$B$292,0)) -> Accessories | C11: =INDEX('Raw Data'!$F$5:$F$292,MATCH(A11,'Raw Data'!$B$5:$B$292,0)) -> 7000 | D11: =INDEX('Raw Data'!$G$5:$G$292,MATCH(A11,'Raw Data'!$B$5:$B$292,0)) -> 4000 | E11: =SUMIFS('Raw Data'!$E$5:$E$292,'Raw Data'!$B$5:$B$292,A11) -> 1037 | F11: =SUMIFS('Raw Data'!$K$5:$K$292,'Raw Data'!$B$5:$B$292,A11) -> 7259000 | G11: =SUMIFS('Raw Data'!$L$5:$L$292,'Raw Data'!$B$5:$B$292,A11) -> 4148000 | H11: =F11-G11 -> 3111000 | I11: =IFERROR(H11/F11,0) -> 0.42857143 | J11: =IFERROR(F11/SUM($F$5:$F$12),0) -> 0.072834725 | K11: =IFERROR((SUMIFS('Raw Data'!$K$5:$K$292,'Raw Data'!$B$5:$B$292,A11,'Raw Data'!$D$5:$D$292,"December")/SUMIFS('Raw Data'!$K$5:$K$292,'Raw Data'!$B$5:$B$292,A11,'Raw Data'!$D$5:$D$292,"January"))-1,0) -> 0.45070423 | L11: =RANK(F11,$F$5:$F$12,0) -> 7
A12: Sticky Notes | B12: =INDEX('Raw Data'!$C$5:$C$292,MATCH(A12,'Raw Data'!$B$5:$B$292,0)) -> Paper Products | C12: =INDEX('Raw Data'!$F$5:$F$292,MATCH(A12,'Raw Data'!$B$5:$B$292,0)) -> 15000 | D12: =INDEX('Raw Data'!$G$5:$G$292,MATCH(A12,'Raw Data'!$B$5:$B$292,0)) -> 9000 | E12: =SUMIFS('Raw Data'!$E$5:$E$292,'Raw Data'!$B$5:$B$292,A12) -> 850 | F12: =SUMIFS('Raw Data'!$K$5:$K$292,'Raw Data'!$B$5:$B$292,A12) -> 12750000 | G12: =SUMIFS('Raw Data'!$L$5:$L$292,'Raw Data'!$B$5:$B$292,A12) -> 7650000 | H12: =F12-G12 -> 5100000 | I12: =IFERROR(H12/F12,0) -> 0.4 | J12: =IFERROR(F12/SUM($F$5:$F$12),0) -> 0.12792984 | K12: =IFERROR((SUMIFS('Raw Data'!$K$5:$K$292,'Raw Data'!$B$5:$B$292,A12,'Raw Data'!$D$5:$D$292,"December")/SUMIFS('Raw Data'!$K$5:$K$292,'Raw Data'!$B$5:$B$292,A12,'Raw Data'!$D$5:$D$292,"January"))-1,0) -> 0.40677966 | L12: =RANK(F12,$F$5:$F$12,0) -> 3

Sheet Branch Analysis
A1: BRANCH ANALYSIS
A2: Compare branch performance and category contribution
A4: BRANCH PERFORMANCE
A5: Branch | B5: Revenue (Rp) | C5: Units Sold | D5: Gross Profit (Rp) | E5: Margin % | F5: Rank
A6: Bandung | B6: =SUMIFS('Raw Data'!$K$5:$K$292,'Raw Data'!$A$5:$A$292,A6) -> 33140000 | C6: =SUMIFS('Raw Data'!$E$5:$E$292,'Raw Data'!$A$5:$A$292,A6) -> 4072 | D6: =SUMIFS('Raw Data'!$M$5:$M$292,'Raw Data'!$A$5:$A$292,A6) -> 12865400 | E6: =IFERROR(D6/B6,0) -> 0.38821364 | F6: =RANK(B6,$B$6:$B$8,0) -> 2
A7: Jakarta | B7: =SUMIFS('Raw Data'!$K$5:$K$292,'Raw Data'!$A$5:$A$292,A7) -> 40817000 | C7: =SUMIFS('Raw Data'!$E$5:$E$292,'Raw Data'!$A$5:$A$292,A7) -> 5011 | D7: =SUMIFS('Raw Data'!$M$5:$M$292,'Raw Data'!$A$5:$A$292,A7) -> 15841800 | E7: =IFERROR(D7/B7,0) -> 0.3881177 | F7: =RANK(B7,$B$6:$B$8,0) -> 1
A8: Surabaya | B8: =SUMIFS('Raw Data'!$K$5:$K$292,'Raw Data'!$A$5:$A$292,A8) -> 25707000 | C8: =SUMIFS('Raw Data'!$E$5:$E$292,'Raw Data'!$A$5:$A$292,A8) -> 3152 | D8: =SUMIFS('Raw Data'!$M$5:$M$292,'Raw Data'!$A$5:$A$292,A8) -> 9975600 | E8: =IFERROR(D8/B8,0) -> 0.38804995 | F8: =RANK(B8,$B$6:$B$8,0) -> 3
A11: CATEGORY BY BRANCH
A12: Branch | B12: Paper Products | C12: Writing Tools | D12: Accessories | E12: Total Revenue | F12: Share of Total
A13: Bandung | B13: =SUMIFS('Raw Data'!$K$5:$K$292,'Raw Data'!$A$5:$A$292,$A13,'Raw Data'!$C$5:$C$292,B$12) -> 14030000 | C13: =SUMIFS('Raw Data'!$K$5:$K$292,'Raw Data'!$A$5:$A$292,$A13,'Raw Data'!$C$5:$C$292,C$12) -> 11095000 | D13: =SUMIFS('Raw Data'!$K$5:$K$292,'Raw Data'!$A$5:$A$292,$A13,'Raw Data'!$C$5:$C$292,D$12) -> 8015000 | E13: =SUM(B13:D13) -> 33140000 | F13: =IFERROR(E13/SUM($E$13:$E$15),0) -> 0.33251726
A14: Jakarta | B14: =SUMIFS('Raw Data'!$K$5:$K$292,'Raw Data'!$A$5:$A$292,$A14,'Raw Data'!$C$5:$C$292,B$12) -> 17350000 | C14: =SUMIFS('Raw Data'!$K$5:$K$292,'Raw Data'!$A$5:$A$292,$A14,'Raw Data'!$C$5:$C$292,C$12) -> 13605000 | D14: =SUMIFS('Raw Data'!$K$5:$K$292,'Raw Data'!$A$5:$A$292,$A14,'Raw Data'!$C$5:$C$292,D$12) -> 9862000 | E14: =SUM(B14:D14) -> 40817000 | F14: =IFERROR(E14/SUM($E$13:$E$15),0) -> 0.40954607
A15: Surabaya | B15: =SUMIFS('Raw Data'!$K$5:$K$292,'Raw Data'!$A$5:$A$292,$A15,'Raw Data'!$C$5:$C$292,B$12) -> 10920000 | C15: =SUMIFS('Raw Data'!$K$5:$K$292,'Raw Data'!$A$5:$A$292,$A15,'Raw Data'!$C$5:$C$292,C$12) -> 8563000 | D15: =SUMIFS('Raw Data'!$K$5:$K$292,'Raw Data'!$A$5:$A$292,$A15,'Raw Data'!$C$5:$C$292,D$12) -> 6224000 | E15: =SUM(B15:D15) -> 25707000 | F15: =IFERROR(E15/SUM($E$13:$E$15),0) -> 0.25793667

Sheet Monthly Analysis
A1: MONTHLY ANALYSIS
A2: Revenue, units, profit and month-over-month growth
A4: Month | B4: Revenue (Rp) | C4: Units Sold | D4: COGS (Rp) | E4: Gross Profit (Rp) | F4: Margin % | G4: MoM Growth | H4: Revenue Index
A5: January | B5: =SUMIFS('Raw Data'!$K$5:$K$292,'Raw Data'!$D$5:$D$292,A5) -> 6906000 | C5: =SUMIFS('Raw Data'!$E$5:$E$292,'Raw Data'!$D$5:$D$292,A5) -> 855 | D5: =SUMIFS('Raw Data'!$L$5:$L$292,'Raw Data'!$D$5:$D$292,A5) -> 4221200 | E5: =SUMIFS('Raw Data'!$M$5:$M$292,'Raw Data'!$D$5:$D$292,A5) -> 2684800 | F5: =IFERROR(E5/B5,0) -> 0.38876339 | G5: N/A | H5: =IFERROR(B5/$B$5,0) -> 1
A6: February | B6: =SUMIFS('Raw Data'!$K$5:$K$292,'Raw Data'!$D$5:$D$292,A6) -> 7224000 | C6: =SUMIFS('Raw Data'!$E$5:$E$292,'Raw Data'!$D$5:$D$292,A6) -> 880 | D6: =SUMIFS('Raw Data'!$L$5:$L$292,'Raw Data'!$D$5:$D$292,A6) -> 4422800 | E6: =SUMIFS('Raw Data'!$M$5:$M$292,'Raw Data'!$D$5:$D$292,A6) -> 2801200 | F6: =IFERROR(E6/B6,0) -> 0.38776301 | G6: =IFERROR(B6/B5-1,0) -> 0.046046916 | H6: =IFERROR(B6/$B$5,0) -> 1.0460469
A7: March | B7: =SUMIFS('Raw Data'!$K$5:$K$292,'Raw Data'!$D$5:$D$292,A7) -> 7440000 | C7: =SUMIFS('Raw Data'!$E$5:$E$292,'Raw Data'!$D$5:$D$292,A7) -> 919 | D7: =SUMIFS('Raw Data'!$L$5:$L$292,'Raw Data'!$D$5:$D$292,A7) -> 4551800 | E7: =SUMIFS('Raw Data'!$M$5:$M$292,'Raw Data'!$D$5:$D$292,A7) -> 2888200 | F7: =IFERROR(E7/B7,0) -> 0.38819892 | G7: =IFERROR(B7/B6-1,0) -> 0.029900332 | H7: =IFERROR(B7/$B$5,0) -> 1.0773241
A8: April | B8: =SUMIFS('Raw Data'!$K$5:$K$292,'Raw Data'!$D$5:$D$292,A8) -> 7698000 | C8: =SUMIFS('Raw Data'!$E$5:$E$292,'Raw Data'!$D$5:$D$292,A8) -> 945 | D8: =SUMIFS('Raw Data'!$L$5:$L$292,'Raw Data'!$D$5:$D$292,A8) -> 4709000 | E8: =SUMIFS('Raw Data'!$M$5:$M$292,'Raw Data'!$D$5:$D$292,A8) -> 2989000 | F8: =IFERROR(E8/B8,0) -> 0.38828267 | G8: =IFERROR(B8/B7-1,0) -> 0.034677419 | H8: =IFERROR(B8/$B$5,0) -> 1.1146829
A9: May | B9: =SUMIFS('Raw Data'!$K$5:$K$292,'Raw Data'!$D$5:$D$292,A9) -> 7935000 | C9: =SUMIFS('Raw Data'!$E$5:$E$292,'Raw Data'!$D$5:$D$292,A9) -> 972 | D9: =SUMIFS('Raw Data'!$L$5:$L$292,'Raw Data'!$D$5:$D$292,A9) -> 4857800 | E9: =SUMIFS('Raw Data'!$M$5:$M$292,'Raw Data'!$D$5:$D$292,A9) -> 3077200 | F9: =IFERROR(E9/B9,0) -> 0.38780088 | G9: =IFERROR(B9/B8-1,0) -> 0.030787217 | H9: =IFERROR(B9/$B$5,0) -> 1.1490009
A10: June | B10: =SUMIFS('Raw Data'!$K$5:$K$292,'Raw Data'!$D$5:$D$292,A10) -> 8160000 | C10: =SUMIFS('Raw Data'!$E$5:$E$292,'Raw Data'!$D$5:$D$292,A10) -> 1009 | D10: =SUMIFS('Raw Data'!$L$5:$L$292,'Raw Data'!$D$5:$D$292,A10) -> 4988800 | E10: =SUMIFS('Raw Data'!$M$5:$M$292,'Raw Data'!$D$5:$D$292,A10) -> 3171200 | F10: =IFERROR(E10/B10,0) -> 0.38862745 | G10: =IFERROR(B10/B9-1,0) -> 0.028355388 | H10: =IFERROR(B10/$B$5,0) -> 1.1815812
A11: July | B11: =SUMIFS('Raw Data'!$K$5:$K$292,'Raw Data'!$D$5:$D$292,A11) -> 8478000 | C11: =SUMIFS('Raw Data'!$E$5:$E$292,'Raw Data'!$D$5:$D$292,A11) -> 1032 | D11: =SUMIFS('Raw Data'!$L$5:$L$292,'Raw Data'!$D$5:$D$292,A11) -> 5190400 | E11: =SUMIFS('Raw Data'!$M$5:$M$292,'Raw Data'!$D$5:$D$292,A11) -> 3287600 | F11: =IFERROR(E11/B11,0) -> 0.38778014 | G11: =IFERROR(B11/B10-1,0) -> 0.038970588 | H11: =IFERROR(B11/$B$5,0) -> 1.2276281
A12: August | B12: =SUMIFS('Raw Data'!$K$5:$K$292,'Raw Data'!$D$5:$D$292,A12) -> 8655000 | C12: =SUMIFS('Raw Data'!$E$5:$E$292,'Raw Data'!$D$5:$D$292,A12) -> 1067 | D12: =SUMIFS('Raw Data'!$L$5:$L$292,'Raw Data'!$D$5:$D$292,A12) -> 5295200 | E12: =SUMIFS('Raw Data'!$M$5:$M$292,'Raw Data'!$D$5:$D$292,A12) -> 3359800 | F12: =IFERROR(E12/B12,0) -> 0.3881918 | G12: =IFERROR(B12/B11-1,0) -> 0.020877565 | H12: =IFERROR(B12/$B$5,0) -> 1.253258
A13: September | B13: =SUMIFS('Raw Data'!$K$5:$K$292,'Raw Data'!$D$5:$D$292,A13) -> 8895000 | C13: =SUMIFS('Raw Data'!$E$5:$E$292,'Raw Data'!$D$5:$D$292,A13) -> 1093 | D13: =SUMIFS('Raw Data'!$L$5:$L$292,'Raw Data'!$D$5:$D$292,A13) -> 5441000 | E13: =SUMIFS('Raw Data'!$M$5:$M$292,'Raw Data'!$D$5:$D$292,A13) -> 3454000 | F13: =IFERROR(E13/B13,0) -> 0.38830804 | G13: =IFERROR(B13/B12-1,0) -> 0.027729636 | H13: =IFERROR(B13/$B$5,0) -> 1.2880104
A14: October | B14: =SUMIFS('Raw Data'!$K$5:$K$292,'Raw Data'!$D$5:$D$292,A14) -> 9194000 | C14: =SUMIFS('Raw Data'!$E$5:$E$292,'Raw Data'!$D$5:$D$292,A14) -> 1125 | D14: =SUMIFS('Raw Data'!$L$5:$L$292,'Raw Data'!$D$5:$D$292,A14) -> 5628400 | E14: =SUMIFS('Raw Data'!$M$5:$M$292,'Raw Data'!$D$5:$D$292,A14) -> 3565600 | F14: =IFERROR(E14/B14,0) -> 0.38781814 | G14: =IFERROR(B14/B13-1,0) -> 0.03361439 | H14: =IFERROR(B14/$B$5,0) -> 1.3313061
A15: November | B15: =SUMIFS('Raw Data'!$K$5:$K$292,'Raw Data'!$D$5:$D$292,A15) -> 9384000 | C15: =SUMIFS('Raw Data'!$E$5:$E$292,'Raw Data'!$D$5:$D$292,A15) -> 1158 | D15: =SUMIFS('Raw Data'!$L$5:$L$292,'Raw Data'!$D$5:$D$292,A15) -> 5738600 | E15: =SUMIFS('Raw Data'!$M$5:$M$292,'Raw Data'!$D$5:$D$292,A15) -> 3645400 | F15: =IFERROR(E15/B15,0) -> 0.38846974 | G15: =IFERROR(B15/B14-1,0) -> 0.020665652 | H15: =IFERROR(B15/$B$5,0) -> 1.3588184
A16: December | B16: =SUMIFS('Raw Data'!$K$5:$K$292,'Raw Data'!$D$5:$D$292,A16) -> 9695000 | C16: =SUMIFS('Raw Data'!$E$5:$E$292,'Raw Data'!$D$5:$D$292,A16) -> 1180 | D16: =SUMIFS('Raw Data'!$L$5:$L$292,'Raw Data'!$D$5:$D$292,A16) -> 5936200 | E16: =SUMIFS('Raw Data'!$M$5:$M$292,'Raw Data'!$D$5:$D$292,A16) -> 3758800 | F16: =IFERROR(E16/B16,0) -> 0.387705 | G16: =IFERROR(B16/B15-1,0) -> 0.033141517 | H16: =IFERROR(B16/$B$5,0) -> 1.4038517

Sheet Customer Analysis
A1: CUSTOMER & SALES REP ANALYSIS
A2: Contribution by customer and sales representative
A4: CUSTOMER PERFORMANCE | G4: SALES REP PERFORMANCE
A5: Customer | B5: Revenue (Rp) | C5: Units Sold | D5: Revenue Share | E5: Rank | G5: Sales Rep | H5: Revenue (Rp) | I5: Revenue Share
A6: CV Anugerah Sejahtera | B6: =SUMIFS('Raw Data'!$K$5:$K$292,'Raw Data'!$I$5:$I$292,A6) -> 8704000 | C6: =SUMIFS('Raw Data'!$E$5:$E$292,'Raw Data'!$I$5:$I$292,A6) -> 1062 | D6: =IFERROR(B6/SUM($B$6:$B$14),0) -> 0.08733344 | E6: =RANK(B6,$B$6:$B$14,0) -> 7 | G6: Andi Prasetyo | H6: =SUMIFS('Raw Data'!$K$5:$K$292,'Raw Data'!$H$5:$H$292,G6) -> 16453000 | I6: =IFERROR(H6/SUM($H$6:$H$11),0) -> 0.16508468
A7: CV Sumber Makmur | B7: =SUMIFS('Raw Data'!$K$5:$K$292,'Raw Data'!$I$5:$I$292,A7) -> 11047000 | C7: =SUMIFS('Raw Data'!$E$5:$E$292,'Raw Data'!$I$5:$I$292,A7) -> 1347 | D7: =IFERROR(B7/SUM($B$6:$B$14),0) -> 0.11084243 | E7: =RANK(B7,$B$6:$B$14,0) -> 5 | G7: Budi Santoso | H7: =SUMIFS('Raw Data'!$K$5:$K$292,'Raw Data'!$H$5:$H$292,G7) -> 20349000 | I7: =IFERROR(H7/SUM($H$6:$H$11),0) -> 0.20417603
A8: Kantor Pratama Abadi | B8: =SUMIFS('Raw Data'!$K$5:$K$292,'Raw Data'!$I$5:$I$292,A8) -> 13696000 | C8: =SUMIFS('Raw Data'!$E$5:$E$292,'Raw Data'!$I$5:$I$292,A8) -> 1682 | D8: =IFERROR(B8/SUM($B$6:$B$14),0) -> 0.13742174 | E8: =RANK(B8,$B$6:$B$14,0) -> 1 | G8: Dedi Hermawan | H8: =SUMIFS('Raw Data'!$K$5:$K$292,'Raw Data'!$H$5:$H$292,G8) -> 12812000 | I8: =IFERROR(H8/SUM($H$6:$H$11),0) -> 0.12855193
A9: PT Media Kreasi | B9: =SUMIFS('Raw Data'!$K$5:$K$292,'Raw Data'!$I$5:$I$292,A9) -> 13553000 | C9: =SUMIFS('Raw Data'!$E$5:$E$292,'Raw Data'!$I$5:$I$292,A9) -> 1673 | D9: =IFERROR(B9/SUM($B$6:$B$14),0) -> 0.13598692 | E9: =RANK(B9,$B$6:$B$14,0) -> 3 | G9: Maya Kusuma | H9: =SUMIFS('Raw Data'!$K$5:$K$292,'Raw Data'!$H$5:$H$292,G9) -> 20468000 | I9: =IFERROR(H9/SUM($H$6:$H$11),0) -> 0.20537004
A10: Sekolah Tunas Bangsa | B10: =SUMIFS('Raw Data'!$K$5:$K$292,'Raw Data'!$I$5:$I$292,A10) -> 11119000 | C10: =SUMIFS('Raw Data'!$E$5:$E$292,'Raw Data'!$I$5:$I$292,A10) -> 1365 | D10: =IFERROR(B10/SUM($B$6:$B$14),0) -> 0.11156486 | E10: =RANK(B10,$B$6:$B$14,0) -> 4 | G10: Rina Anggraini | H10: =SUMIFS('Raw Data'!$K$5:$K$292,'Raw Data'!$H$5:$H$292,G10) -> 12895000 | I10: =IFERROR(H10/SUM($H$6:$H$11),0) -> 0.12938473
A11: Toko Berkah Jaya | B11: =SUMIFS('Raw Data'!$K$5:$K$292,'Raw Data'!$I$5:$I$292,A11) -> 10974000 | C11: =SUMIFS('Raw Data'!$E$5:$E$292,'Raw Data'!$I$5:$I$292,A11) -> 1360 | D11: =IFERROR(B11/SUM($B$6:$B$14),0) -> 0.11010997 | E11: =RANK(B11,$B$6:$B$14,0) -> 6 | G11: Sri Wulandari | H11: =SUMIFS('Raw Data'!$K$5:$K$292,'Raw Data'!$H$5:$H$292,G11) -> 16687000 | I11: =IFERROR(H11/SUM($H$6:$H$11),0) -> 0.16743257
A12: Toko Cahaya Ilmu | B12: =SUMIFS('Raw Data'!$K$5:$K$292,'Raw Data'!$I$5:$I$292,A12) -> 13568000 | C12: =SUMIFS('Raw Data'!$E$5:$E$292,'Raw Data'!$I$5:$I$292,A12) -> 1656 | D12: =IFERROR(B12/SUM($B$6:$B$14),0) -> 0.13613742 | E12: =RANK(B12,$B$6:$B$14,0) -> 2
A13: Toko Ceria | B13: =SUMIFS('Raw Data'!$K$5:$K$292,'Raw Data'!$I$5:$I$292,A13) -> 8521000 | C13: =SUMIFS('Raw Data'!$E$5:$E$292,'Raw Data'!$I$5:$I$292,A13) -> 1053 | D13: =IFERROR(B13/SUM($B$6:$B$14),0) -> 0.085497271 | E13: =RANK(B13,$B$6:$B$14,0) -> 8
A14: Yayasan Pendidikan Nusantara | B14: =SUMIFS('Raw Data'!$K$5:$K$292,'Raw Data'!$I$5:$I$292,A14) -> 8482000 | C14: =SUMIFS('Raw Data'!$E$5:$E$292,'Raw Data'!$I$5:$I$292,A14) -> 1037 | D14: =IFERROR(B14/SUM($B$6:$B$14),0) -> 0.085105956 | E14: =RANK(B14,$B$6:$B$14,0) -> 9

Sheet Summary
A1: EXECUTIVE SUMMARY
A2: A short summary of the sales portfolio
A4: KEY METRICS | F4: TOP PERFORMERS
A5: Metric | B5: Result | C5: Formula / Source | D5: Comment | F5: Item | G5: Result
A6: Total Revenue | B6: =SUM('Raw Data'!$K$5:$K$292) -> 99664000 | C6: Raw Data / Revenue | D6: Total sales value | F6: Top Branch | G6: =INDEX('Branch Analysis'!$A$6:$A$8,MATCH(MAX('Branch Analysis'!$B$6:$B$8),'Branch Analysis'!$B$6:$B$8,0)) -> Jakarta
A7: Gross Profit | B7: =SUM('Raw Data'!$M$5:$M$292) -> 38682800 | C7: Revenue - COGS | D7: Profit before other expenses | F7: Top Product | G7: =INDEX('Sales Analysis'!$A$5:$A$12,MATCH(MAX('Sales Analysis'!$F$5:$F$12),'Sales Analysis'!$F$5:$F$12,0)) -> Notebook
A8: Gross Margin | B8: =IFERROR(B7/B6,0) -> 0.38813212 | C8: Gross Profit / Revenue | D8: Overall gross margin | F8: Best Month | G8: =INDEX('Monthly Analysis'!$A$5:$A$16,MATCH(MAX('Monthly Analysis'!$B$5:$B$16),'Monthly Analysis'!$B$5:$B$16,0)) -> December
A9: Units Sold | B9: =SUM('Raw Data'!$E$5:$E$292) -> 12235 | C9: Raw Data / Units Sold | D9: Total units sold | F9: Highest Margin Branch | G9: =INDEX('Branch Analysis'!$A$6:$A$8,MATCH(MAX('Branch Analysis'!$E$6:$E$8),'Branch Analysis'!$E$6:$E$8,0)) -> Bandung
A10: Transactions | B10: =COUNTA('Raw Data'!$A$5:$A$292) -> 288 | C10: Raw Data rows | D10: Number of transaction rows
A11: Avg Revenue / Transaction | B11: =IFERROR(B6/B10,0) -> 346055.56 | C11: Revenue / Transactions | D11: Average revenue per row
A14: OBSERVATIONS
A15: 1. Branch margins are nearly identical (Bandung 38.82%, Jakarta 38.81%, Surabaya 38.80%), so Jakarta's revenue being 59% higher than Surabaya comes purely from market and volume scale, not a difference in operational efficiency.
A17: 2. Notebook is the largest revenue contributor (29.6% of total) but also has the thinnest margin (32.0%), the lowest of all 8 products. Opportunity: push cross-sell of Eraser/Ruler (45% and 42.9% margin) to Notebook buyers to lift margin without sacrificing volume.
A19: 3. Notebook is also the fastest-growing product from January to December (+46.3%), which makes it the main growth driver but also the biggest drag on margin. This pattern is worth tracking monthly, not just reviewed once at year-end.
A21: 4. Revenue from the top 2 sales reps (Maya Kusuma and Budi Santoso) makes up 41% of total sales, a fairly high concentration in 2 out of 6 people. This signals a dependency on specific individuals that the team should keep an eye on.
A24: 5. Monthly revenue grew consistently with no decline at all from January to December (index 1.00x to 1.40x, +40%), a stable growth trend rather than a one-off seasonal spike that's prone to dropping back down.

Sheet Calculations
A1: CALCULATIONS
A2: Helper tables that feed the dashboard charts
A4: Month | B4: Revenue | C4: Gross Profit | D4: Units | F4: Product | G4: Revenue | I4: Branch | J4: Revenue | L4: Category | M4: Revenue
A5: January | B5: =IF(Dashboard!$F$4="All Branches",SUMIFS('Raw Data'!$K$5:$K$292,'Raw Data'!$D$5:$D$292,A5),SUMIFS('Raw Data'!$K$5:$K$292,'Raw Data'!$D$5:$D$292,A5,'Raw Data'!$A$5:$A$292,Dashboard!$F$4)) -> 6906000 | C5: =IF(Dashboard!$F$4="All Branches",SUMIFS('Raw Data'!$M$5:$M$292,'Raw Data'!$D$5:$D$292,A5),SUMIFS('Raw Data'!$M$5:$M$292,'Raw Data'!$D$5:$D$292,A5,'Raw Data'!$A$5:$A$292,Dashboard!$F$4)) -> 2684800 | D5: =IF(Dashboard!$F$4="All Branches",SUMIFS('Raw Data'!$E$5:$E$292,'Raw Data'!$D$5:$D$292,A5),SUMIFS('Raw Data'!$E$5:$E$292,'Raw Data'!$D$5:$D$292,A5,'Raw Data'!$A$5:$A$292,Dashboard!$F$4)) -> 855 | F5: Ballpoint Pen | G5: =IF(Dashboard!$F$4="All Branches",SUMIFS('Raw Data'!$K$5:$K$292,'Raw Data'!$B$5:$B$292,F5),SUMIFS('Raw Data'!$K$5:$K$292,'Raw Data'!$B$5:$B$292,F5,'Raw Data'!$A$5:$A$292,Dashboard!$F$4)) -> 14165000 | I5: Bandung | J5: =SUMIFS('Raw Data'!$K$5:$K$292,'Raw Data'!$A$5:$A$292,I5) -> 33140000 | L5: Accessories | M5: =SUMIFS('Raw Data'!$K$5:$K$292,'Raw Data'!$C$5:$C$292,L5) -> 24101000
A6: February | B6: =IF(Dashboard!$F$4="All Branches",SUMIFS('Raw Data'!$K$5:$K$292,'Raw Data'!$D$5:$D$292,A6),SUMIFS('Raw Data'!$K$5:$K$292,'Raw Data'!$D$5:$D$292,A6,'Raw Data'!$A$5:$A$292,Dashboard!$F$4)) -> 7224000 | C6: =IF(Dashboard!$F$4="All Branches",SUMIFS('Raw Data'!$M$5:$M$292,'Raw Data'!$D$5:$D$292,A6),SUMIFS('Raw Data'!$M$5:$M$292,'Raw Data'!$D$5:$D$292,A6,'Raw Data'!$A$5:$A$292,Dashboard!$F$4)) -> 2801200 | D6: =IF(Dashboard!$F$4="All Branches",SUMIFS('Raw Data'!$E$5:$E$292,'Raw Data'!$D$5:$D$292,A6),SUMIFS('Raw Data'!$E$5:$E$292,'Raw Data'!$D$5:$D$292,A6,'Raw Data'!$A$5:$A$292,Dashboard!$F$4)) -> 880 | F6: Correction Tape | G6: =IF(Dashboard!$F$4="All Branches",SUMIFS('Raw Data'!$K$5:$K$292,'Raw Data'!$B$5:$B$292,F6),SUMIFS('Raw Data'!$K$5:$K$292,'Raw Data'!$B$5:$B$292,F6,'Raw Data'!$A$5:$A$292,Dashboard!$F$4)) -> 10206000 | I6: Jakarta | J6: =SUMIFS('Raw Data'!$K$5:$K$292,'Raw Data'!$A$5:$A$292,I6) -> 40817000 | L6: Paper Products | M6: =SUMIFS('Raw Data'!$K$5:$K$292,'Raw Data'!$C$5:$C$292,L6) -> 42300000
A7: March | B7: =IF(Dashboard!$F$4="All Branches",SUMIFS('Raw Data'!$K$5:$K$292,'Raw Data'!$D$5:$D$292,A7),SUMIFS('Raw Data'!$K$5:$K$292,'Raw Data'!$D$5:$D$292,A7,'Raw Data'!$A$5:$A$292,Dashboard!$F$4)) -> 7440000 | C7: =IF(Dashboard!$F$4="All Branches",SUMIFS('Raw Data'!$M$5:$M$292,'Raw Data'!$D$5:$D$292,A7),SUMIFS('Raw Data'!$M$5:$M$292,'Raw Data'!$D$5:$D$292,A7,'Raw Data'!$A$5:$A$292,Dashboard!$F$4)) -> 2888200 | D7: =IF(Dashboard!$F$4="All Branches",SUMIFS('Raw Data'!$E$5:$E$292,'Raw Data'!$D$5:$D$292,A7),SUMIFS('Raw Data'!$E$5:$E$292,'Raw Data'!$D$5:$D$292,A7,'Raw Data'!$A$5:$A$292,Dashboard!$F$4)) -> 919 | F7: Eraser | G7: =IF(Dashboard!$F$4="All Branches",SUMIFS('Raw Data'!$K$5:$K$292,'Raw Data'!$B$5:$B$292,F7),SUMIFS('Raw Data'!$K$5:$K$292,'Raw Data'!$B$5:$B$292,F7,'Raw Data'!$A$5:$A$292,Dashboard!$F$4)) -> 6636000 | I7: Surabaya | J7: =SUMIFS('Raw Data'!$K$5:$K$292,'Raw Data'!$A$5:$A$292,I7) -> 25707000 | L7: Writing Tools | M7: =SUMIFS('Raw Data'!$K$5:$K$292,'Raw Data'!$C$5:$C$292,L7) -> 33263000
A8: April | B8: =IF(Dashboard!$F$4="All Branches",SUMIFS('Raw Data'!$K$5:$K$292,'Raw Data'!$D$5:$D$292,A8),SUMIFS('Raw Data'!$K$5:$K$292,'Raw Data'!$D$5:$D$292,A8,'Raw Data'!$A$5:$A$292,Dashboard!$F$4)) -> 7698000 | C8: =IF(Dashboard!$F$4="All Branches",SUMIFS('Raw Data'!$M$5:$M$292,'Raw Data'!$D$5:$D$292,A8),SUMIFS('Raw Data'!$M$5:$M$292,'Raw Data'!$D$5:$D$292,A8,'Raw Data'!$A$5:$A$292,Dashboard!$F$4)) -> 2989000 | D8: =IF(Dashboard!$F$4="All Branches",SUMIFS('Raw Data'!$E$5:$E$292,'Raw Data'!$D$5:$D$292,A8),SUMIFS('Raw Data'!$E$5:$E$292,'Raw Data'!$D$5:$D$292,A8,'Raw Data'!$A$5:$A$292,Dashboard!$F$4)) -> 945 | F8: Highlighter | G8: =IF(Dashboard!$F$4="All Branches",SUMIFS('Raw Data'!$K$5:$K$292,'Raw Data'!$B$5:$B$292,F8),SUMIFS('Raw Data'!$K$5:$K$292,'Raw Data'!$B$5:$B$292,F8,'Raw Data'!$A$5:$A$292,Dashboard!$F$4)) -> 11304000
A9: May | B9: =IF(Dashboard!$F$4="All Branches",SUMIFS('Raw Data'!$K$5:$K$292,'Raw Data'!$D$5:$D$292,A9),SUMIFS('Raw Data'!$K$5:$K$292,'Raw Data'!$D$5:$D$292,A9,'Raw Data'!$A$5:$A$292,Dashboard!$F$4)) -> 7935000 | C9: =IF(Dashboard!$F$4="All Branches",SUMIFS('Raw Data'!$M$5:$M$292,'Raw Data'!$D$5:$D$292,A9),SUMIFS('Raw Data'!$M$5:$M$292,'Raw Data'!$D$5:$D$292,A9,'Raw Data'!$A$5:$A$292,Dashboard!$F$4)) -> 3077200 | D9: =IF(Dashboard!$F$4="All Branches",SUMIFS('Raw Data'!$E$5:$E$292,'Raw Data'!$D$5:$D$292,A9),SUMIFS('Raw Data'!$E$5:$E$292,'Raw Data'!$D$5:$D$292,A9,'Raw Data'!$A$5:$A$292,Dashboard!$F$4)) -> 972 | F9: Notebook | G9: =IF(Dashboard!$F$4="All Branches",SUMIFS('Raw Data'!$K$5:$K$292,'Raw Data'!$B$5:$B$292,F9),SUMIFS('Raw Data'!$K$5:$K$292,'Raw Data'!$B$5:$B$292,F9,'Raw Data'!$A$5:$A$292,Dashboard!$F$4)) -> 29550000
A10: June | B10: =IF(Dashboard!$F$4="All Branches",SUMIFS('Raw Data'!$K$5:$K$292,'Raw Data'!$D$5:$D$292,A10),SUMIFS('Raw Data'!$K$5:$K$292,'Raw Data'!$D$5:$D$292,A10,'Raw Data'!$A$5:$A$292,Dashboard!$F$4)) -> 8160000 | C10: =IF(Dashboard!$F$4="All Branches",SUMIFS('Raw Data'!$M$5:$M$292,'Raw Data'!$D$5:$D$292,A10),SUMIFS('Raw Data'!$M$5:$M$292,'Raw Data'!$D$5:$D$292,A10,'Raw Data'!$A$5:$A$292,Dashboard!$F$4)) -> 3171200 | D10: =IF(Dashboard!$F$4="All Branches",SUMIFS('Raw Data'!$E$5:$E$292,'Raw Data'!$D$5:$D$292,A10),SUMIFS('Raw Data'!$E$5:$E$292,'Raw Data'!$D$5:$D$292,A10,'Raw Data'!$A$5:$A$292,Dashboard!$F$4)) -> 1009 | F10: Pencil | G10: =IF(Dashboard!$F$4="All Branches",SUMIFS('Raw Data'!$K$5:$K$292,'Raw Data'!$B$5:$B$292,F10),SUMIFS('Raw Data'!$K$5:$K$292,'Raw Data'!$B$5:$B$292,F10,'Raw Data'!$A$5:$A$292,Dashboard!$F$4)) -> 7794000
A11: July | B11: =IF(Dashboard!$F$4="All Branches",SUMIFS('Raw Data'!$K$5:$K$292,'Raw Data'!$D$5:$D$292,A11),SUMIFS('Raw Data'!$K$5:$K$292,'Raw Data'!$D$5:$D$292,A11,'Raw Data'!$A$5:$A$292,Dashboard!$F$4)) -> 8478000 | C11: =IF(Dashboard!$F$4="All Branches",SUMIFS('Raw Data'!$M$5:$M$292,'Raw Data'!$D$5:$D$292,A11),SUMIFS('Raw Data'!$M$5:$M$292,'Raw Data'!$D$5:$D$292,A11,'Raw Data'!$A$5:$A$292,Dashboard!$F$4)) -> 3287600 | D11: =IF(Dashboard!$F$4="All Branches",SUMIFS('Raw Data'!$E$5:$E$292,'Raw Data'!$D$5:$D$292,A11),SUMIFS('Raw Data'!$E$5:$E$292,'Raw Data'!$D$5:$D$292,A11,'Raw Data'!$A$5:$A$292,Dashboard!$F$4)) -> 1032 | F11: Ruler | G11: =IF(Dashboard!$F$4="All Branches",SUMIFS('Raw Data'!$K$5:$K$292,'Raw Data'!$B$5:$B$292,F11),SUMIFS('Raw Data'!$K$5:$K$292,'Raw Data'!$B$5:$B$292,F11,'Raw Data'!$A$5:$A$292,Dashboard!$F$4)) -> 7259000
A12: August | B12: =IF(Dashboard!$F$4="All Branches",SUMIFS('Raw Data'!$K$5:$K$292,'Raw Data'!$D$5:$D$292,A12),SUMIFS('Raw Data'!$K$5:$K$292,'Raw Data'!$D$5:$D$292,A12,'Raw Data'!$A$5:$A$292,Dashboard!$F$4)) -> 8655000 | C12: =IF(Dashboard!$F$4="All Branches",SUMIFS('Raw Data'!$M$5:$M$292,'Raw Data'!$D$5:$D$292,A12),SUMIFS('Raw Data'!$M$5:$M$292,'Raw Data'!$D$5:$D$292,A12,'Raw Data'!$A$5:$A$292,Dashboard!$F$4)) -> 3359800 | D12: =IF(Dashboard!$F$4="All Branches",SUMIFS('Raw Data'!$E$5:$E$292,'Raw Data'!$D$5:$D$292,A12),SUMIFS('Raw Data'!$E$5:$E$292,'Raw Data'!$D$5:$D$292,A12,'Raw Data'!$A$5:$A$292,Dashboard!$F$4)) -> 1067 | F12: Sticky Notes | G12: =IF(Dashboard!$F$4="All Branches",SUMIFS('Raw Data'!$K$5:$K$292,'Raw Data'!$B$5:$B$292,F12),SUMIFS('Raw Data'!$K$5:$K$292,'Raw Data'!$B$5:$B$292,F12,'Raw Data'!$A$5:$A$292,Dashboard!$F$4)) -> 12750000
A13: September | B13: =IF(Dashboard!$F$4="All Branches",SUMIFS('Raw Data'!$K$5:$K$292,'Raw Data'!$D$5:$D$292,A13),SUMIFS('Raw Data'!$K$5:$K$292,'Raw Data'!$D$5:$D$292,A13,'Raw Data'!$A$5:$A$292,Dashboard!$F$4)) -> 8895000 | C13: =IF(Dashboard!$F$4="All Branches",SUMIFS('Raw Data'!$M$5:$M$292,'Raw Data'!$D$5:$D$292,A13),SUMIFS('Raw Data'!$M$5:$M$292,'Raw Data'!$D$5:$D$292,A13,'Raw Data'!$A$5:$A$292,Dashboard!$F$4)) -> 3454000 | D13: =IF(Dashboard!$F$4="All Branches",SUMIFS('Raw Data'!$E$5:$E$292,'Raw Data'!$D$5:$D$292,A13),SUMIFS('Raw Data'!$E$5:$E$292,'Raw Data'!$D$5:$D$292,A13,'Raw Data'!$A$5:$A$292,Dashboard!$F$4)) -> 1093
A14: October | B14: =IF(Dashboard!$F$4="All Branches",SUMIFS('Raw Data'!$K$5:$K$292,'Raw Data'!$D$5:$D$292,A14),SUMIFS('Raw Data'!$K$5:$K$292,'Raw Data'!$D$5:$D$292,A14,'Raw Data'!$A$5:$A$292,Dashboard!$F$4)) -> 9194000 | C14: =IF(Dashboard!$F$4="All Branches",SUMIFS('Raw Data'!$M$5:$M$292,'Raw Data'!$D$5:$D$292,A14),SUMIFS('Raw Data'!$M$5:$M$292,'Raw Data'!$D$5:$D$292,A14,'Raw Data'!$A$5:$A$292,Dashboard!$F$4)) -> 3565600 | D14: =IF(Dashboard!$F$4="All Branches",SUMIFS('Raw Data'!$E$5:$E$292,'Raw Data'!$D$5:$D$292,A14),SUMIFS('Raw Data'!$E$5:$E$292,'Raw Data'!$D$5:$D$292,A14,'Raw Data'!$A$5:$A$292,Dashboard!$F$4)) -> 1125
A15: November | B15: =IF(Dashboard!$F$4="All Branches",SUMIFS('Raw Data'!$K$5:$K$292,'Raw Data'!$D$5:$D$292,A15),SUMIFS('Raw Data'!$K$5:$K$292,'Raw Data'!$D$5:$D$292,A15,'Raw Data'!$A$5:$A$292,Dashboard!$F$4)) -> 9384000 | C15: =IF(Dashboard!$F$4="All Branches",SUMIFS('Raw Data'!$M$5:$M$292,'Raw Data'!$D$5:$D$292,A15),SUMIFS('Raw Data'!$M$5:$M$292,'Raw Data'!$D$5:$D$292,A15,'Raw Data'!$A$5:$A$292,Dashboard!$F$4)) -> 3645400 | D15: =IF(Dashboard!$F$4="All Branches",SUMIFS('Raw Data'!$E$5:$E$292,'Raw Data'!$D$5:$D$292,A15),SUMIFS('Raw Data'!$E$5:$E$292,'Raw Data'!$D$5:$D$292,A15,'Raw Data'!$A$5:$A$292,Dashboard!$F$4)) -> 1158
A16: December | B16: =IF(Dashboard!$F$4="All Branches",SUMIFS('Raw Data'!$K$5:$K$292,'Raw Data'!$D$5:$D$292,A16),SUMIFS('Raw Data'!$K$5:$K$292,'Raw Data'!$D$5:$D$292,A16,'Raw Data'!$A$5:$A$292,Dashboard!$F$4)) -> 9695000 | C16: =IF(Dashboard!$F$4="All Branches",SUMIFS('Raw Data'!$M$5:$M$292,'Raw Data'!$D$5:$D$292,A16),SUMIFS('Raw Data'!$M$5:$M$292,'Raw Data'!$D$5:$D$292,A16,'Raw Data'!$A$5:$A$292,Dashboard!$F$4)) -> 3758800 | D16: =IF(Dashboard!$F$4="All Branches",SUMIFS('Raw Data'!$E$5:$E$292,'Raw Data'!$D$5:$D$292,A16),SUMIFS('Raw Data'!$E$5:$E$292,'Raw Data'!$D$5:$D$292,A16,'Raw Data'!$A$5:$A$292,Dashboard!$F$4)) -> 1180
